typingchat/__about__.py
typingchat/__init__.py
typingchat/chat.py
typingchat/core.py
typingchat-0.0.1.dist-info/METADATA
typingchat-0.0.1.dist-info/WHEEL
typingchat-0.0.1.dist-info/RECORD
