Metadata-Version: 2.3
Name: typingchat
Version: 0.0.1
Summary: A python style implementation of Typechat.
Project-URL: Repository, https://github.com/liqzz/typingchat
Author: liqzz
License-Expression: MIT
Classifier: Programming Language :: Python
Classifier: Programming Language :: Python :: 3.11
Classifier: Programming Language :: Python :: 3.12
Classifier: Programming Language :: Python :: Implementation :: CPython
Classifier: Programming Language :: Python :: Implementation :: PyPy
Requires-Python: >=3.10
Requires-Dist: openai>=1.25.2
Requires-Dist: pydantic>=2.7.1
